LICENSE
README.rst
setup.py
BLACKFORGE2/CURSEWORK.py
BLACKFORGE2/__init__.py
BLACKFORGE2.egg-info/PKG-INFO
BLACKFORGE2.egg-info/SOURCES.txt
BLACKFORGE2.egg-info/dependency_links.txt
BLACKFORGE2.egg-info/requires.txt
BLACKFORGE2.egg-info/top_level.txt